.DS_Store
sydsvenskan/__init__.py
sydsvenskan/newsday.py
sydsvenskan/search.py
sydsvenskan-0.3.0.dist-info/METADATA
sydsvenskan-0.3.0.dist-info/RECORD
sydsvenskan-0.3.0.dist-info/WHEEL
sydsvenskan-0.3.0.dist-info/top_level.txt
