Metadata-Version: 2.1
Name: sydsvenskan
Version: 0.3.0
Summary: Module for searching sydsvenskan.se
Home-page: https://github.com/peterstark72/py-sydsvenskan
Author: Peter Stark
Author-email: peterstark72@gmail.com
License: MIT License
Requires-Dist: requests (>=2.19.1)
Requires-Dist: lxml (>=4.2.3)
Requires-Dist: pyRFC3339 (>=1.1)
